ipyturtle/__init__.py
ipyturtle/_version.py
ipyturtle/example.py
ipyturtle/static/extension.js
ipyturtle/static/index.js
ipyturtle/static/index.js.map
ipyturtle-0.2.4.data/data/etc/jupyter/nbconfig/notebook.d/ipyturtle.json
ipyturtle-0.2.4.data/data/share/jupyter/nbextensions/ipyturtle/extension.js
ipyturtle-0.2.4.data/data/share/jupyter/nbextensions/ipyturtle/index.js
ipyturtle-0.2.4.data/data/share/jupyter/nbextensions/ipyturtle/index.js.map
ipyturtle-0.2.4.dist-info/LICENSE
ipyturtle-0.2.4.dist-info/METADATA
ipyturtle-0.2.4.dist-info/WHEEL
ipyturtle-0.2.4.dist-info/top_level.txt
ipyturtle-0.2.4.dist-info/RECORD
