Metadata-Version: 2.1
Name: ipyturtle
Version: 0.2.4
Summary: Creating Turtle Geometry in IPython (Jupyter Widget)
Home-page: https://github.com/gkvoelkl/ipython-turtle-widget
Author: gkvoelkl
Author-email: gkvoelkl@nelson-games.de
License: UNKNOWN
Keywords: ipython,jupyter,widgets
Platform: UNKNOWN
Classifier: Development Status :: 4 - Beta
Classifier: Framework :: IPython
Classifier: Intended Audience :: Developers
Classifier: Intended Audience :: Science/Research
Classifier: Topic :: Multimedia :: Graphics
Classifier: Programming Language :: Python :: 2
Classifier: Programming Language :: Python :: 2.7
Classifier: Programming Language :: Python :: 3
Classifier: Programming Language :: Python :: 3.3
Classifier: Programming Language :: Python :: 3.4
Classifier: Programming Language :: Python :: 3.5
Requires-Dist: ipywidgets (>=7.0.0)
